gotty_py/__init__.py
gotty_py/gotty_client.py
gotty_py-1.0.2.dist-info/licenses/LICENSE
gotty_py-1.0.2.dist-info/METADATA
gotty_py-1.0.2.dist-info/WHEEL
gotty_py-1.0.2.dist-info/top_level.txt
gotty_py-1.0.2.dist-info/RECORD
