Metadata-Version: 2.4
Name: gotty-py
Version: 1.0.2
Summary: A generic Python client for interacting with gotty terminal interfaces
Home-page: https://github.com/twentworth/gotty-py
Author: Thomas Wentworth
Author-email: Thomas Wentworth <thomaswentworth@example.com>
Maintainer-email: Thomas Wentworth <thomaswentworth@example.com>
License: MIT
Project-URL: Homepage, https://github.com/twentworth/gotty-py
Project-URL: Documentation, https://github.com/twentworth/gotty-py#readme
Project-URL: Repository, https://github.com/twentworth/gotty-py.git
Project-URL: Bug Tracker, https://github.com/twentworth/gotty-py/issues
Project-URL: Changelog, https://github.com/twentworth/gotty-py/blob/main/CHANGELOG.md
Keywords: gotty,websocket,terminal,client,tty
Classifier: Development Status :: 4 - Beta
Classifier: Intended Audience :: Developers
Classifier: License :: OSI Approved :: MIT License
Classifier: Operating System :: OS Independent
Classifier: Programming Language :: Python :: 3
Classifier: Programming Language :: Python :: 3.8
Classifier: Programming Language :: Python :: 3.9
Classifier: Programming Language :: Python :: 3.10
Classifier: Programming Language :: Python :: 3.11
Classifier: Programming Language :: Python :: 3.12
Classifier: Programming Language :: Python :: 3.13
Classifier: Topic :: Communications
Classifier: Topic :: Internet :: WWW/HTTP :: Dynamic Content
Classifier: Topic :: Software Development :: Libraries :: Python Modules
Classifier: Topic :: System :: Networking
Classifier: Topic :: Terminals
Requires-Python: >=3.8
License-File: LICENSE
Requires-Dist: websockets>=11.0.3
Requires-Dist: requests>=2.31.0
Provides-Extra: dev
Requires-Dist: pytest>=7.4.2; extra == "dev"
Requires-Dist: pytest-cov>=4.1.0; extra == "dev"
Requires-Dist: black>=23.7.0; extra == "dev"
Requires-Dist: mypy>=1.5.1; extra == "dev"
Requires-Dist: flake8>=6.0.0; extra == "dev"
Requires-Dist: isort>=5.12.0; extra == "dev"
Provides-Extra: test
Requires-Dist: pytest>=7.4.2; extra == "test"
Requires-Dist: pytest-cov>=4.1.0; extra == "test"
Dynamic: author
Dynamic: home-page
Dynamic: license-file
Dynamic: requires-python
